cefin/__init__.py
cefin/data_api.py
cefin-0.2.dist-info/LICENSE
cefin-0.2.dist-info/METADATA
cefin-0.2.dist-info/WHEEL
cefin-0.2.dist-info/top_level.txt
cefin-0.2.dist-info/RECORD
