Metadata-Version: 2.2
Name: cefin
Version: 0.2
Summary: Repository of Insper's Finance Unit
Author: Insper's Finance Unit
Maintainer: Insper's Finance Unit
Maintainer-email: cefim@insper.edu.br
Keywords: finance,financial data
License-File: LICENSE
Requires-Dist: pandas
Requires-Dist: requests
Dynamic: author
Dynamic: description
Dynamic: description-content-type
Dynamic: keywords
Dynamic: maintainer
Dynamic: maintainer-email
Dynamic: requires-dist
Dynamic: summary
